odoo/addons/partner_contact_old_migration_fields/README.rst
odoo/addons/partner_contact_old_migration_fields/__init__.py
odoo/addons/partner_contact_old_migration_fields/__manifest__.py
odoo/addons/partner_contact_old_migration_fields/i18n/es.po
odoo/addons/partner_contact_old_migration_fields/models/__init__.py
odoo/addons/partner_contact_old_migration_fields/models/res_partner.py
odoo/addons/partner_contact_old_migration_fields/readme/CONTRIBUTORS.md
odoo/addons/partner_contact_old_migration_fields/readme/DESCRIPTION.md
odoo/addons/partner_contact_old_migration_fields/readme/USAGE.md
odoo/addons/partner_contact_old_migration_fields/static/description/icon.png
odoo/addons/partner_contact_old_migration_fields/static/description/index.html
odoo/addons/partner_contact_old_migration_fields/views/res_partner_views.xml
odoo_addon_partner_contact_old_migration_fields-18.0.1.0.0.1.dist-info/METADATA
odoo_addon_partner_contact_old_migration_fields-18.0.1.0.0.1.dist-info/WHEEL
odoo_addon_partner_contact_old_migration_fields-18.0.1.0.0.1.dist-info/top_level.txt
odoo_addon_partner_contact_old_migration_fields-18.0.1.0.0.1.dist-info/RECORD
